README.md
setup.py
pycallback/__init__.py
pycallback.egg-info/PKG-INFO
pycallback.egg-info/SOURCES.txt
pycallback.egg-info/dependency_links.txt
pycallback.egg-info/top_level.txt