Metadata-Version: 1.2
Name: pycallback
Version: 0.1.0
Summary: simple callback wrapper for python
Home-page: https://github.com/williamfzc/pycallback
Author: williamfzc
Author-email: fengzc@vip.qq.com
License: MIT
Platform: UNKNOWN
Classifier: License :: OSI Approved :: MIT License
Classifier: Programming Language :: Python
Classifier: Programming Language :: Python :: 3
Classifier: Programming Language :: Python :: 3.6
Classifier: Programming Language :: Python :: 3.7
Classifier: Programming Language :: Python :: 3.8
Requires-Python: >=3.6
